trendspy/__init__.py
trendspy/client.py
trendspy/constants.py
trendspy/converter.py
trendspy/hierarchical_search.py
trendspy/news_article.py
trendspy/timeframe_utils.py
trendspy/trend_keyword.py
trendspy/trend_list.py
trendspy/utils.py
trendspy-0.1.6.dist-info/METADATA
trendspy-0.1.6.dist-info/WHEEL
trendspy-0.1.6.dist-info/licenses/LICENSE
trendspy-0.1.6.dist-info/RECORD
