Metadata-Version: 2.4
Name: trendspy
Version: 0.1.6
Summary: A Python library for accessing Google Trends data
Project-URL: Homepage, https://github.com/sdil87/trendspy
Project-URL: Repository, https://github.com/sdil87/trendspy.git
Project-URL: Issues, https://github.com/sdil87/trendspy/issues
Author: SDil
License: MIT License
License-File: LICENSE
Keywords: analytics,data-analysis,google-trends,trends
Classifier: Development Status :: 4 - Beta
Classifier: Intended Audience :: Developers
Classifier: Intended Audience :: Science/Research
Classifier: License :: OSI Approved :: MIT License
Classifier: Operating System :: OS Independent
Classifier: Programming Language :: Python :: 3
Classifier: Programming Language :: Python :: 3.7
Classifier: Programming Language :: Python :: 3.8
Classifier: Programming Language :: Python :: 3.9
Classifier: Programming Language :: Python :: 3.10
Classifier: Programming Language :: Python :: 3.11
Classifier: Topic :: Internet
Classifier: Topic :: Scientific/Engineering :: Information Analysis
Classifier: Topic :: Software Development :: Libraries :: Python Modules
Requires-Python: >=3.7
Requires-Dist: numpy>=1.19.0
Requires-Dist: pandas>=1.2.0
Requires-Dist: python-dateutil>=2.8.0
Requires-Dist: requests>=2.25.0
